tonoi/__init__.py
tonoi/canvas.py
tonoi/exceptions.py
tonoi/handlers.py
tonoi/intrinsics.py
tonoi/misc.py
tonoi/termutils.py
tonoi/tonoi.py
tonoi-0.2.0.dist-info/METADATA
tonoi-0.2.0.dist-info/WHEEL
tonoi-0.2.0.dist-info/entry_points.txt
tonoi-0.2.0.dist-info/top_level.txt
tonoi-0.2.0.dist-info/RECORD
